subutai_bazaar
