Metadata-Version: 2.1
Name: subutai-bazaar
Version: 0.0.6
Summary: Library for Subutai Bazaar REST API
Home-page: https://github.com/crioto/subutai-bazaar
Author: crioto
Author-email: msavochkin@optdyn.com
License: UNKNOWN
Platform: UNKNOWN
Classifier: Programming Language :: Python :: 3
Classifier: License :: OSI Approved :: GNU General Public License v3 (GPLv3)
Classifier: Operating System :: OS Independent
Requires-Python: >=3.6
